setup.py
pymyra/__init__.py
pymyra.egg-info/PKG-INFO
pymyra.egg-info/SOURCES.txt
pymyra.egg-info/dependency_links.txt
pymyra.egg-info/requires.txt
pymyra.egg-info/top_level.txt
pymyra/api/__init__.py
pymyra/api/client.py