Metadata-Version: 1.1
Name: pymyra
Version: 1.0.5
Summary: Myra SDK for Python 2.x.
Home-page: https://github.com/myralabs/pymyra
Author: The Myra Team
Author-email: info@myralabs.com
License: MIT
Keywords: artificial intelligence nlp api myra machine learning
Platform: UNKNOWN
Classifier: Development Status :: 3 - Alpha
Classifier: Intended Audience :: Developers
Classifier: Topic :: Software Development :: Build Tools
Classifier: License :: OSI Approved :: MIT License
Classifier: Programming Language :: Python :: 2.7
